netimport_lib/__init__.py
netimport_lib/cli.py
netimport_lib/config_loader.py
netimport_lib/graph_builder/__init__.py
netimport_lib/graph_builder/graph_builder.py
netimport_lib/graph_builder/resolver_imports.py
netimport_lib/imports_reader.py
netimport_lib/project_file_reader.py
netimport_lib/summary_builder.py
netimport_lib/visualizer/__init__.py
netimport_lib/visualizer/bokeh_plotter_v2.py
netimport_lib/visualizer/mpl_plotter.py
netimport_lib/visualizer/plotly_plotter.py
netimport-0.0.7.dist-info/LICENSE.txt
netimport-0.0.7.dist-info/METADATA
netimport-0.0.7.dist-info/WHEEL
netimport-0.0.7.dist-info/entry_points.txt
netimport-0.0.7.dist-info/RECORD
