Metadata-Version: 2.3
Name: netimport
Version: 0.0.7
Summary: NetImport: Python Project Architecture Analyzer via Import Graphs
License: MIT
Keywords: python,architecture,linter,static analysis,import graph,dependencies,visualization,coupling,cohesion
Author: Beilak Aliev
Author-email: beilak.aliev@gmail.com
Requires-Python: >=3.10
Classifier: Development Status :: 3 - Alpha
Classifier: Environment :: Console
Classifier: Intended Audience :: Developers
Classifier: License :: OSI Approved :: MIT License
Classifier: Operating System :: OS Independent
Classifier: Programming Language :: Python :: 3
Classifier: Programming Language :: Python :: 3.10
Classifier: Programming Language :: Python :: 3.11
Classifier: Programming Language :: Python :: 3.12
Classifier: Programming Language :: Python :: 3.13
Classifier: Programming Language :: Python :: 3.9
Classifier: Topic :: Software Development :: Libraries :: Python Modules
Classifier: Topic :: Software Development :: Quality Assurance
Classifier: Topic :: Utilities
Classifier: Typing :: Typed
Requires-Dist: bokeh (>=3.7.3,<4.0.0)
Requires-Dist: click (>=8.2.1,<9.0.0)
Requires-Dist: matplotlib (>=3.10.3,<4.0.0)
Requires-Dist: networkx (>=3.4.2,<4.0.0)
Requires-Dist: numpy (>=2.0.1,<3.0.0)
Requires-Dist: plotly (>=6.1.2,<7.0.0)
Requires-Dist: toml (>=0.10.2,<0.11.0)
Project-URL: Homepage, https://github.com/beilak/netimport
Project-URL: Repository, https://github.com/beilak/netimport
